Metadata-Version: 1.1
Name: addoneexample
Version: 0.0.1
Summary: A very basic function which adds 1 to any number
Home-page: UNKNOWN
Author: Isaac Cobb
Author-email: cobbcoding@gmail.com
License: MIT
Keywords: add one
Platform: UNKNOWN
Classifier: Development Status :: 5 - Production/Stable
Classifier: Intended Audience :: Education
Classifier: Operating System :: Microsoft :: Windows :: Windows 10
Classifier: License :: OSI Approved :: MIT License
Classifier: Programming Language :: Python :: 3
